google_scraper_pw/__init__.py
google_scraper_pw/get_page_pw.py
google_scraper_pw/google_tr.py
google_scraper_pw/google_tr_async.py-
google_scraper_pw-0.1.0.dist-info/WHEEL
google_scraper_pw-0.1.0.dist-info/METADATA
google_scraper_pw-0.1.0.dist-info/RECORD
