Metadata-Version: 2.1
Name: google-scraper-pw
Version: 0.1.0
Summary: scrape google via playwright
Home-page: https://github.com/ffreemt/google-scraper-playwright
License: MIT
Author: freemt
Requires-Python: >=3.7,<4.0
Classifier: License :: OSI Approved :: MIT License
Classifier: Programming Language :: Python :: 3
Classifier: Programming Language :: Python :: 3.7
Classifier: Programming Language :: Python :: 3.8
Classifier: Programming Language :: Python :: 3.9
Requires-Dist: get-pwbrowser (>=0.1.1,<0.2.0)
Requires-Dist: linetimer (>=0.1.4,<0.2.0)
Requires-Dist: logzero (>=1.6.3,<2.0.0)
Requires-Dist: playwright (>=1.10.0,<2.0.0)
Project-URL: Repository, https://github.com/ffreemt/google-scraper-playwright
